ripple_detector_CNN/RippleDetectorCNN.py
ripple_detector_CNN/__init__.py
ripple_detector_CNN/define_ripple_candidates.py
ripple_detector_CNN/ResNet1D/ResNet1D.py
ripple_detector_CNN/ResNet1D/__init__.py
ripple_detector_CNN/ResNet1D/modules.py
ripple_detector_CNN/data/ResNet1D.yaml
ripple_detector_CNN/external/__init__.py
ripple_detector_CNN/external/modified_ripple_detection/__init__.py
ripple_detector_CNN/external/modified_ripple_detection/core.py
ripple_detector_CNN-0.1.5.dist-info/LICENSE
ripple_detector_CNN-0.1.5.dist-info/METADATA
ripple_detector_CNN-0.1.5.dist-info/WHEEL
ripple_detector_CNN-0.1.5.dist-info/top_level.txt
ripple_detector_CNN-0.1.5.dist-info/RECORD
